np_iafp/__init__.py
np_iafp-0.0.1.dist-info/LICENSE.txt
np_iafp-0.0.1.dist-info/METADATA
np_iafp-0.0.1.dist-info/WHEEL
np_iafp-0.0.1.dist-info/top_level.txt
np_iafp-0.0.1.dist-info/RECORD
