Metadata-Version: 2.1
Name: np-iafp
Version: 0.0.1
Summary: A tool to find out the prime numbers that a number contains.
Home-page: UNKNOWN
Author: Nacho Fontal
Author-email: nachofp613@gmail.com
License: MIT License
Keywords: prime mathematical number prime_numbers
Platform: UNKNOWN
Classifier: Development Status :: 4 - Beta
Classifier: Intended Audience :: Developers
Classifier: Topic :: Utilities
Classifier: License :: OSI Approved :: MIT License
Classifier: Programming Language :: Python :: 3
Classifier: Operating System :: OS Independent
